compiloor/__init__.py
compiloor/compiloor-report/config.json
compiloor/compiloor-report/sections/about_author_content.md
compiloor/compiloor-report/sections/about_protocol_content.md
compiloor/compiloor-report/sections/disclaimer_content.md
compiloor/compiloor-report/sections/introduction_content.md
compiloor/compiloor-report/sections/security_assessment_summary_content.md
compiloor/constants/__init__.py
compiloor/constants/environment.py
compiloor/constants/logger.py
compiloor/constants/report.py
compiloor/constants/utils.py
compiloor/main.py
compiloor/services/__init__.py
compiloor/services/cli/__init__.py
compiloor/services/cli/cli.py
compiloor/services/environment/__init__.py
compiloor/services/environment/setup.py
compiloor/services/environment/utils.py
compiloor/services/logger/__init__.py
compiloor/services/logger/logger.py
compiloor/services/parser/__init__.py
compiloor/services/parser/chromium.py
compiloor/services/parser/finding.py
compiloor/services/parser/indexing.py
compiloor/services/parser/legend.py
compiloor/services/parser/markdown.py
compiloor/services/parser/table.py
compiloor/services/parser/utils.py
compiloor/services/typings/__init__.py
compiloor/services/typings/config.py
compiloor/services/typings/finding.py
compiloor/services/utils/__init__.py
compiloor/services/utils/config.py
compiloor/services/utils/utils.py
compiloor-0.2.8.dist-info/METADATA
compiloor-0.2.8.dist-info/WHEEL
compiloor-0.2.8.dist-info/entry_points.txt
compiloor-0.2.8.dist-info/RECORD
