Metadata-Version: 2.1
Name: compiloor
Version: 0.2.8
Summary: 
Author: Kristian Apostolov
Author-email: kristianapostolovcontacts@gmail.com
Requires-Python: >=3.11,<4.0
Classifier: Programming Language :: Python :: 3
Classifier: Programming Language :: Python :: 3.11
Requires-Dist: attrs (==23.1.0)
Requires-Dist: beautifulsoup4 (==4.12.2)
Requires-Dist: brotli (==1.1.0)
Requires-Dist: build (==0.10.0)
Requires-Dist: cachecontrol (==0.13.1)
Requires-Dist: certifi (==2023.7.22)
Requires-Dist: cffi (==1.16.0)
Requires-Dist: charset-normalizer (==3.3.0)
Requires-Dist: cleo (==2.0.1)
Requires-Dist: click (==8.1.7)
Requires-Dist: crashtest (==0.4.1)
Requires-Dist: cryptography (==41.0.4)
Requires-Dist: cssselect2 (==0.7.0)
Requires-Dist: defusedxml (==0.7.1)
Requires-Dist: distlib (==0.3.7)
Requires-Dist: docopt (==0.6.2)
Requires-Dist: dulwich (==0.21.6)
Requires-Dist: filelock (==3.13.0)
Requires-Dist: fonttools (==4.43.0)
Requires-Dist: greenlet (==2.0.2)
Requires-Dist: h11 (==0.14.0)
Requires-Dist: html5lib (==1.1)
Requires-Dist: idna (==3.4)
Requires-Dist: importlib-metadata (==6.8.0)
Requires-Dist: install (==1.3.5)
Requires-Dist: installer (==0.7.0)
Requires-Dist: jaraco-classes (==3.3.0)
Requires-Dist: jsonschema (==4.17.3)
Requires-Dist: keyring (==24.2.0)
Requires-Dist: markdown (==3.4.4)
Requires-Dist: markdown-it-py (==3.0.0)
Requires-Dist: markdown2 (==2.4.10)
Requires-Dist: mdurl (==0.1.2)
Requires-Dist: mistune (==3.0.2)
Requires-Dist: more-itertools (==10.1.0)
Requires-Dist: msgpack (==1.0.7)
Requires-Dist: outcome (==1.2.0)
Requires-Dist: packaging (==23.2)
Requires-Dist: pexpect (==4.8.0)
Requires-Dist: pillow (==10.0.1)
Requires-Dist: pkginfo (==1.9.6)
Requires-Dist: platformdirs (==3.11.0)
Requires-Dist: playwright (==1.38.0)
Requires-Dist: poetry (==1.6.1)
Requires-Dist: poetry-core (==1.7.0)
Requires-Dist: poetry-plugin-export (==1.5.0)
Requires-Dist: ptyprocess (==0.7.0)
Requires-Dist: pycparser (==2.21)
Requires-Dist: pydyf (==0.8.0)
Requires-Dist: pyee (==9.0.4)
Requires-Dist: pygments (==2.16.1)
Requires-Dist: pymdown-extensions (==10.3)
Requires-Dist: pymupdf (==1.23.4)
Requires-Dist: pymupdfb (==1.23.3)
Requires-Dist: pyphen (==0.14.0)
Requires-Dist: pyproject-hooks (==1.0.0)
Requires-Dist: pyrsistent (==0.20.0)
Requires-Dist: pysocks (==1.7.1)
Requires-Dist: pyyaml (==6.0.1)
Requires-Dist: rapidfuzz (==2.15.2)
Requires-Dist: requests (==2.31.0)
Requires-Dist: requests-toolbelt (==1.0.0)
Requires-Dist: rich (==13.6.0)
Requires-Dist: shellingham (==1.5.4)
Requires-Dist: six (==1.16.0)
Requires-Dist: sniffio (==1.3.0)
Requires-Dist: sortedcontainers (==2.4.0)
Requires-Dist: soupsieve (==2.5)
Requires-Dist: svgwrite (==1.4.3)
Requires-Dist: tabulate (==0.9.0)
Requires-Dist: tinycss2 (==1.2.1)
Requires-Dist: tomlkit (==0.12.1)
Requires-Dist: trio (==0.22.2)
Requires-Dist: trio-websocket (==0.11.1)
Requires-Dist: trove-classifiers (==2023.10.18)
Requires-Dist: typer (==0.9.0)
Requires-Dist: typing-extensions (==4.8.0)
Requires-Dist: urllib3 (==2.0.6)
Requires-Dist: virtualenv (==20.24.6)
Requires-Dist: wavedrom (==2.0.3.post3)
Requires-Dist: weasyprint (==60.1)
Requires-Dist: webencodings (==0.5.1)
Requires-Dist: wsproto (==1.2.0)
Requires-Dist: xattr (==0.10.1)
Requires-Dist: zipp (==3.17.0)
Requires-Dist: zopfli (==0.2.3)
